timelab/__init__.py
timelab/core/__init__.py
timelab/core/base.py
timelab/core/total_time.py
timelab/datetime/__init__.py
timelab/datetime/datetime.py
timelab/timespan/__init__.py
timelab/timespan/timespan.py
timelab-1.0.dist-info/METADATA
timelab-1.0.dist-info/WHEEL
timelab-1.0.dist-info/top_level.txt
timelab-1.0.dist-info/RECORD
