Metadata-Version: 2.1
Name: timelab
Version: 1.0
Summary: Python time engine.
Author: Schkimansky
Author-email: <ahmadchawla1432@gmail.com>
Keywords: python,time,engine,lab,timelab,datetime,date,time,manager
Classifier: Development Status :: 5 - Production/Stable
Classifier: Intended Audience :: Developers
Classifier: Programming Language :: Python :: 3
Classifier: Operating System :: Unix
Classifier: Operating System :: MacOS :: MacOS X
Classifier: Operating System :: Microsoft :: Windows
